apimatic_twilio_sdk-1.0.0.dist-info/licenses/LICENSE
twilioapiexplorer/__init__.py
twilioapiexplorer/api_helper.py
twilioapiexplorer/configuration.py
twilioapiexplorer/twilioapiexplorer_client.py
twilioapiexplorer/controllers/__init__.py
twilioapiexplorer/controllers/access_tokens_controller.py
twilioapiexplorer/controllers/accounts_controller.py
twilioapiexplorer/controllers/actions_controller.py
twilioapiexplorer/controllers/activities_controller.py
twilioapiexplorer/controllers/addresses_controller.py
twilioapiexplorer/controllers/alphasenders_controller.py
twilioapiexplorer/controllers/applications_controller.py
twilioapiexplorer/controllers/assets_controller.py
twilioapiexplorer/controllers/assistants_controller.py
twilioapiexplorer/controllers/available_phone_number_countries_controller.py
twilioapiexplorer/controllers/base_controller.py
twilioapiexplorer/controllers/bindings_controller.py
twilioapiexplorer/controllers/buckets_controller.py
twilioapiexplorer/controllers/builds_controller.py
twilioapiexplorer/controllers/caller_ids_controller.py
twilioapiexplorer/controllers/calls_controller.py
twilioapiexplorer/controllers/challenges_controller.py
twilioapiexplorer/controllers/chat_bindings_controller.py
twilioapiexplorer/controllers/chat_channel_webhook_controller.py
twilioapiexplorer/controllers/chat_channels_controller.py
twilioapiexplorer/controllers/chat_credentials_controller.py
twilioapiexplorer/controllers/chat_invites_controller.py
twilioapiexplorer/controllers/chat_members_controller.py
twilioapiexplorer/controllers/chat_messages_controller.py
twilioapiexplorer/controllers/chat_roles_controller.py
twilioapiexplorer/controllers/chat_services_controller.py
twilioapiexplorer/controllers/chat_user_channels_controller.py
twilioapiexplorer/controllers/chat_users_controller.py
twilioapiexplorer/controllers/commands_controller.py
twilioapiexplorer/controllers/composition_hooks_controller.py
twilioapiexplorer/controllers/composition_settings_controller.py
apimatic_twilio_sdk-1.0.0.dist-info/METADATA
apimatic_twilio_sdk-1.0.0.dist-info/WHEEL
apimatic_twilio_sdk-1.0.0.dist-info/top_level.txt
apimatic_twilio_sdk-1.0.0.dist-info/RECORD
